pyec/__init__.py
pyec/benchmark.py
pyec/curve.py
pyec/curve_params.py
pyec/maths.py
pyec/point.py
pyec/sign.py
pyelcurve-0.1.0.dist-info/METADATA
pyelcurve-0.1.0.dist-info/WHEEL
pyelcurve-0.1.0.dist-info/RECORD
