Metadata-Version: 2.1
Name: pyelcurve
Version: 0.1.0
Summary: Elliptic curve arithmetic and digital signatures in Python.
License: MIT
Author: Andrew Shannon
Requires-Python: >=3.9,<4.0
Classifier: License :: OSI Approved :: MIT License
Classifier: Programming Language :: Python :: 3
Classifier: Programming Language :: Python :: 3.9
Classifier: Programming Language :: Python :: 3.10
Classifier: Programming Language :: Python :: 3.11
Classifier: Programming Language :: Python :: 3.12
